django_bootstrap3_form/__init__.py
django_bootstrap3_form/fields.py
django_bootstrap3_form/form.py
django_bootstrap3_form/util.py
django_bootstrap3_form/widgets.py
django_bootstrap3_form/static/django_bootstrap3_form/bootstrap/dist/css/bootstrap-theme.css
django_bootstrap3_form/static/django_bootstrap3_form/bootstrap/dist/css/bootstrap-theme.css.map
django_bootstrap3_form/static/django_bootstrap3_form/bootstrap/dist/css/bootstrap-theme.min.css
django_bootstrap3_form/static/django_bootstrap3_form/bootstrap/dist/css/bootstrap.css
django_bootstrap3_form/static/django_bootstrap3_form/bootstrap/dist/css/bootstrap.css.map
django_bootstrap3_form/static/django_bootstrap3_form/bootstrap/dist/css/bootstrap.min.css
django_bootstrap3_form/static/django_bootstrap3_form/bootstrap/dist/fonts/glyphicons-halflings-regular.eot
django_bootstrap3_form/static/django_bootstrap3_form/bootstrap/dist/fonts/glyphicons-halflings-regular.svg
django_bootstrap3_form/static/django_bootstrap3_form/bootstrap/dist/fonts/glyphicons-halflings-regular.ttf
django_bootstrap3_form/static/django_bootstrap3_form/bootstrap/dist/fonts/glyphicons-halflings-regular.woff
django_bootstrap3_form/static/django_bootstrap3_form/bootstrap/dist/fonts/glyphicons-halflings-regular.woff2
django_bootstrap3_form/static/django_bootstrap3_form/bootstrap/dist/js/bootstrap.js
django_bootstrap3_form/static/django_bootstrap3_form/bootstrap/dist/js/bootstrap.min.js
django_bootstrap3_form/static/django_bootstrap3_form/bootstrap/dist/js/npm.js
django_bootstrap3_form/templates/django_bootstrap3_form/checkbox_widget.html
django_bootstrap3_form/templates/django_bootstrap3_form/errorlist.html
django_bootstrap3_form/templates/django_bootstrap3_form/form.html
django_bootstrap3_form/templates/django_bootstrap3_form/radio_select_widget.html
django_bootstrap3_form/templates/django_bootstrap3_form/row.html
django_bootstrap3_form-1.1.0.dist-info/LICENSE.rst
django_bootstrap3_form-1.1.0.dist-info/METADATA
django_bootstrap3_form-1.1.0.dist-info/WHEEL
django_bootstrap3_form-1.1.0.dist-info/top_level.txt
django_bootstrap3_form-1.1.0.dist-info/RECORD
