Metadata-Version: 2.1
Name: django-bootstrap3-form
Version: 1.1.0
Summary: Django-bootstrap3-form allows you write Django forms that work with Twitter Bootstrap 3
Home-page: https://github.com/mbraak/django-bootstrap3-form
Author: Marco Braak
Author-email: mbraak@ridethepony.nl
License: Apache License, Version 2.0
Platform: UNKNOWN
Classifier: Development Status :: 5 - Production/Stable
Classifier: Framework :: Django
Classifier: Framework :: Django :: 2.2
Classifier: Framework :: Django :: 3.0
Classifier: Framework :: Django :: 3.1
Classifier: Intended Audience :: Developers
Classifier: License :: OSI Approved :: Apache Software License
Classifier: Programming Language :: Python :: 3.6
Classifier: Programming Language :: Python :: 3.7
Classifier: Programming Language :: Python :: 3.8
Classifier: Programming Language :: Python :: Implementation :: CPython
Requires-Dist: Django
Requires-Dist: django-pony-forms
